vtool/distance.py
vtool/quality_classifier.py
vtool/numpy_utils.py
vtool/image_shared.py
vtool/segmentation.py
vtool/clustering2.py
vtool/patch.py
vtool/histogram.py
vtool/depricated.py
vtool/trig.py
vtool/features.py
vtool/inspect_matches.py
vtool/_old_matching.py
vtool/chip.py
vtool/_pyflann_backend.py
vtool/__init__.py
vtool/symbolic.py
vtool/keypoint.py
vtool/other.py
vtool/confusion.py
vtool/_grave.py
vtool/sver_c_wrapper.py
vtool/coverage_grid.py
vtool/_rhomb_dist.py
vtool/blend.py
vtool/ellipse.py
vtool/matching.py
vtool/exif.py
vtool/fontdemo.py
vtool/linalg.py
vtool/image.py
vtool/_version.py
vtool/spatial_verification.py
vtool/image_filters.py
vtool/coverage_kpts.py
vtool/__main__.py
vtool/geometry.py
vtool/util_math.py
vtool/score_normalization.py
vtool/nearest_neighbors.py
vtool/demodata.py
vtool/lib/libsver.so
vtool/lib/libsver.so.4.0.2
vtool/lib/libsver.so.4.0
vtool/lib/libsver_s.a
wbia_vtool-4.0.2.dist-info/METADATA
wbia_vtool-4.0.2.dist-info/WHEEL
wbia_vtool-4.0.2.dist-info/RECORD
wbia_vtool-4.0.2.dist-info/LICENSE
wbia_vtool-4.0.2.dist-info/top_level.txt
wbia_vtool.libs/libgomp-a34b3233.so.1.0.0
wbia_vtool.libs/libopencv_core-26de4276.so.2.4.5
